dexter/__init__.py
dexter/display.py
dexter/framelist.py
dexter/framemap.py
dexter/optimizer.py
dexter/readmultiple.py
dexter-0.0.7.dist-info/LICENSE.txt
dexter-0.0.7.dist-info/METADATA
dexter-0.0.7.dist-info/WHEEL
dexter-0.0.7.dist-info/top_level.txt
dexter-0.0.7.dist-info/RECORD
