Metadata-Version: 2.1
Name: dexter
Version: 0.0.7
Summary: Data Exploration Terser
Home-page: https://github.com/igormagalhaesr/dexter
Author: Igor Magalhaes
Author-email: igor.magalhaes.r@gmail.com
License: BSD 3
Project-URL: Documentation, https://github.com/igormagalhaesr/dexter/blob/main/README.md
Project-URL: Source, https://github.com/igormagalhaesr/dexter
Project-URL: Tracker, https://github.com/igormagalhaesr/dexter/issues
Platform: UNKNOWN
Classifier: Development Status :: 2 - Pre-Alpha
Classifier: License :: OSI Approved :: BSD License
Classifier: Intended Audience :: Science/Research
Classifier: Programming Language :: Python :: 3
Classifier: Programming Language :: Python :: 3 :: Only
Classifier: Programming Language :: Python :: 3.9
Classifier: Topic :: Scientific/Engineering
Classifier: Operating System :: OS Independent
Classifier: Framework :: IPython
License-File: LICENSE.txt
